termremind/__init__.py
termremind/conf.py
termremind/data.py
termremind/main.py
termremind-0.0.4.7.dist-info/LICENSE
termremind-0.0.4.7.dist-info/METADATA
termremind-0.0.4.7.dist-info/WHEEL
termremind-0.0.4.7.dist-info/entry_points.txt
termremind-0.0.4.7.dist-info/top_level.txt
termremind-0.0.4.7.dist-info/RECORD
