Metadata-Version: 2.1
Name: termremind
Version: 0.0.4.7
Summary: Reminders in terminal
Home-page: https://github.com/SomethingGeneric/Remind
Author: Matt C
Author-email: matt@mattcompton.me
License: GPLv3
Keywords: python3 linux system-information
Platform: UNKNOWN
Classifier: Development Status :: 5 - Production/Stable
Classifier: Environment :: Console
Classifier: Intended Audience :: End Users/Desktop
Classifier: Intended Audience :: System Administrators
Classifier: License :: OSI Approved :: GNU General Public License v3 (GPLv3)
Classifier: Natural Language :: English
Classifier: Operating System :: POSIX :: Linux
Classifier: Programming Language :: Python :: 3
Classifier: Programming Language :: Python :: 3.4
Classifier: Programming Language :: Python :: 3.5
Classifier: Programming Language :: Python :: 3.6
Classifier: Programming Language :: Python :: 3.7
Classifier: Programming Language :: Python :: 3.8
Classifier: Programming Language :: Python :: 3.9
Classifier: Topic :: System
Classifier: Topic :: Terminals
Requires-Python: >=3
Requires-Dist: colorama
